{
  "template": "core-skeleton",
  "uiPack": "ui-pack-showcase-greenpink",
  "modules": [
    "feature-showcase"
  ],
  "appName": "浦项制铁",
  "packageName": "com.ndjc.apps.app.sepaid000018",
  "versionCode": 1,
  "versionName": "1.0.0",
  "storeId": "store_showcase_paid_000018",
  "merchantEmail": "whywhy9264@gmail.com",
  "privacyUrl": "https://niandongjicheng.vercel.app/privacy/store_showcase_paid_000018",
  "iconPath": "requests/ndjc-20260423T160422115Z-KI5KL1/icon.png",
  "plan": "pro",
  "firebaseProjectId": "ndjc-paid-03",
  "firebaseCredentialsEnvKey": "FIREBASE_SERVICE_ACCOUNT_NDJC_PAID_03"
}