{
  "runId": "ndjc-20260423T151633980Z-WXZWXV",
  "appName": "洛杉矶银河",
  "moduleName": "feature-showcase",
  "uiPackName": "ui-pack-showcase-greenpink",
  "plan": "pro",
  "storeId": "store_showcase_paid_000017",
  "adminName": "666666@qq.com",
  "status": "running",
  "stage": "matching_logic_module",
  "step": 3,
  "message": "Matching logic module",
  "artifactName": null,
  "workflowRunId": "24843271289",
  "workflowStatus": "in_progress",
  "workflowConclusion": null,
  "workflowUrl": "https://github.com/why459097630/Packaging-warehouse/actions/runs/24843271289",
  "artifactUrl": null,
  "downloadUrl": null,
  "releaseUrl": null,
  "publicApkUrl": null,
  "error": null,
  "failedStep": null,
  "updatedAt": "2026-04-23T15:17:54.292Z"
}
